qtlink/__init__.py
qtlink/util.py
qtlink/dialog/__init__.py
qtlink/dialog/dialog_info.py
qtlink/dialog/dialog_input.py
qtlink/dialog/dialog_table_check.py
qtlink/dialog/dialog_table_display.py
qtlink/mpl_canvas/__init__.py
qtlink/mpl_canvas/mpl_canvas.py
qtlink/table/__init__.py
qtlink/table/table_controller.py
qtlink/table/table_controller_multiple_check.py
qtlink/table/table_controller_single_check.py
qtlink/widgets/__init__.py
qtlink/widgets/drop_widget.py
qtlink/widgets/list_widget.py
qtlink-1.2.21.dist-info/LICENSE
qtlink-1.2.21.dist-info/METADATA
qtlink-1.2.21.dist-info/WHEEL
qtlink-1.2.21.dist-info/top_level.txt
qtlink-1.2.21.dist-info/RECORD
