Metadata-Version: 2.1
Name: qtlink
Version: 1.2.21
Summary: a ui framework based on pyside6
Home-page: https://gitee.com/darlingxyz/qtlink
Author: NanHaiLoong
Author-email: nanhai@163.com
Classifier: Programming Language :: Python :: 3
Classifier: License :: OSI Approved :: MIT License
Classifier: Operating System :: OS Independent
License-File: LICENSE
Requires-Dist: PySide6
